python_omegle/__init__.py
python_omegle/_abstractchat.py
python_omegle/_common.py
python_omegle/chatevent.py
python_omegle/exceptions.py
python_omegle/interestschat.py
python_omegle/randomchat.py
python_omegle/spyeechat.py
python_omegle-1.1.6.dist-info/METADATA
python_omegle-1.1.6.dist-info/RECORD
python_omegle-1.1.6.dist-info/WHEEL
python_omegle-1.1.6.dist-info/top_level.txt
