Metadata-Version: 2.1
Name: python-omegle
Version: 1.1.6
Summary: A simple Python API for the Omegle text chat service
Home-page: https://github.com/coal0/python-omegle
Author: coal0
Author-email: daniel_x3@protonmail.com
License: UNKNOWN
Keywords: omegle chat webchat api
Platform: UNKNOWN
Classifier: Development Status :: 5 - Production/Stable
Classifier: Intended Audience :: Developers
Classifier: License :: OSI Approved :: MIT License
Classifier: Operating System :: OS Independent
Classifier: Programming Language :: Python :: 3 :: Only
Classifier: Topic :: Communications :: Chat
Requires-Dist: requests
